cnotebook/__init__.py
cnotebook/align.py
cnotebook/context.py
cnotebook/helpers.py
cnotebook/ipython_ext.py
cnotebook/marimo_ext.py
cnotebook/pandas_ext.py
cnotebook/render.py
cnotebook-1.1.0.dist-info/licenses/LICENSE
cnotebook-1.1.0.dist-info/METADATA
cnotebook-1.1.0.dist-info/WHEEL
cnotebook-1.1.0.dist-info/top_level.txt
cnotebook-1.1.0.dist-info/RECORD
