Metadata-Version: 2.4
Name: cnotebook
Version: 1.1.0
Summary: Chemistry visualization in Jupyter Notebooks with the OpenEye Toolkits
Author-email: Scott Arne Johnson <scott.arne.johnson@gmail.com>
License-Expression: MIT
Project-URL: Homepage, https://github.com/scott-arne/cnotebook
Project-URL: Bug Reports, https://github.com/scott-arne/cnotebook/issues
Project-URL: Source, https://github.com/scott-arne/cnotebook
Project-URL: Documentation, https://github.com/scott-arne/cnotebook#readme
Project-URL: Changelog, https://github.com/scott-arne/cnotebook/blob/master/CHANGELOG.md
Keywords: chemistry,cheminformatics,computational-chemistry,molecular-visualization,jupyter,marimo,openeye,scientific-computing
Classifier: Development Status :: 5 - Production/Stable
Classifier: Intended Audience :: Science/Research
Classifier: Intended Audience :: Developers
Classifier: Topic :: Scientific/Engineering :: Chemistry
Classifier: Topic :: Scientific/Engineering :: Visualization
Classifier: Programming Language :: Python :: 3
Classifier: Programming Language :: Python :: 3.10
Classifier: Programming Language :: Python :: 3.11
Classifier: Programming Language :: Python :: 3.12
Classifier: Programming Language :: Python :: 3 :: Only
Classifier: Operating System :: OS Independent
Classifier: Framework :: Jupyter
Classifier: Framework :: IPython
Requires-Python: >=3.10
License-File: LICENSE
Requires-Dist: pandas<3.0.0,>=2.0.0
Requires-Dist: oepandas>=2.0.0
Requires-Dist: openeye-toolkits
Provides-Extra: dev
Requires-Dist: invoke; extra == "dev"
Requires-Dist: build; extra == "dev"
Requires-Dist: pytest; extra == "dev"
Provides-Extra: test
Requires-Dist: pytest; extra == "test"
Requires-Dist: pytest-cov; extra == "test"
Dynamic: license-file
